ice/__init__.py
ice/api/__init__.py
ice/api/hypergraph.py
ice/api/utils.py
ice/api/scripts/__init__.py
ice/api/scripts/wait_process.py
ice/api/transforms/__init__.py
ice/api/transforms/random.py
ice/api/transforms/semseg.py
ice/api/transforms/image/__init__.py
ice/api/transforms/image/io.py
ice/api/transforms/image/photometric.py
ice/api/transforms/image/spatial.py
ice/core/__init__.py
ice/core/dataset.py
ice/core/graph.py
ice/core/hypergraph.py
ice/core/loss.py
ice/core/metric.py
ice/core/module.py
ice/core/optim.py
ice/llutil/__init__.py
ice/llutil/argparser.py
ice/llutil/backup_src.py
ice/llutil/board.py
ice/llutil/collections.py
ice/llutil/config.py
ice/llutil/debug.py
ice/llutil/dictprocess.py
ice/llutil/file_client.py
ice/llutil/ignore_me.py
ice/llutil/logger.py
ice/llutil/print.py
ice/llutil/pycuda.py
ice/llutil/shadow_tb.py
ice/llutil/test.py
ice/llutil/timer.py
ice/llutil/utils.py
ice/llutil/launcher/__init__.py
ice/llutil/launcher/elastic_multiprocessing.py
ice/llutil/launcher/events.py
ice/llutil/launcher/launch_agent.py
ice/llutil/launcher/launcher.py
ice/llutil/launcher/local_elastic_agent.py
ice/llutil/multiprocessing/__init__.py
ice/llutil/multiprocessing/_atfork.py
ice/llutil/multiprocessing/pool.py
ice/llutil/multiprocessing/queue.py
ice/llutil/multiprocessing/reductions.py
ice/llutil/multiprocessing/reductions_1_10.py
ice/llutil/multiprocessing/reductions_1_11.py
ice/llutil/multiprocessing/spawn.py
ice_learn-0.4.8.dist-info/LICENSE
ice_learn-0.4.8.dist-info/METADATA
ice_learn-0.4.8.dist-info/WHEEL
ice_learn-0.4.8.dist-info/entry_points.txt
ice_learn-0.4.8.dist-info/top_level.txt
ice_learn-0.4.8.dist-info/RECORD
