Metadata-Version: 2.1
Name: ice-learn
Version: 0.4.8
Summary: A high-level Deep Learning framework that extends PyTorch and PyCUDA.
Home-page: https://github.com/tjyuyao/ice-learn
Author: Yuyao Huang
Author-email: huangyuyao@outlook.com
Project-URL: Bug Tracker, https://github.com/tjyuyao/ice-learn/issues
Keywords: keywords = PyTorch,PyCUDA,Deep Learning framework,Multi-Task Learning,multiprocessing
Classifier: Programming Language :: Python :: 3
Classifier: License :: OSI Approved :: MIT License
Classifier: Operating System :: OS Independent
Requires-Python: >=3.7
License-File: LICENSE
Requires-Dist: neurlink (>=0.2.2)
Requires-Dist: multiprocess (>=0.70.12)
Requires-Dist: PySocks (>=1.7.1)
Requires-Dist: varname (>=0.8.1)
Requires-Dist: opencv-python (>=4.5.5)
Requires-Dist: tqdm (>=4.62.3)
Requires-Dist: tensorboard (>=2.8.0)
Requires-Dist: setuptools (>=59.5.0)
Requires-Dist: gputil (>=1.4.0)
Provides-Extra: dev
Requires-Dist: pytest (>=6.2.5) ; extra == 'dev'
Requires-Dist: xdoctest (>=0.15.10) ; extra == 'dev'
Requires-Dist: Pygments (>=2.11.2) ; extra == 'dev'
Requires-Dist: yapf (>=0.32.0) ; extra == 'dev'
Requires-Dist: mkdocs (>=1.2.3) ; extra == 'dev'
Requires-Dist: mkdocs-awesome-pages-plugin (>=2.6.1) ; extra == 'dev'
Requires-Dist: mkdocs-material (>=8.1.8) ; extra == 'dev'
Requires-Dist: python-markdown-math (>=0.8) ; extra == 'dev'
